AUTHORS
CHANGES
LICENSE
MANIFEST.in
README.md
setup.py
pimpmyclass/__init__.py
pimpmyclass/common.py
pimpmyclass/dictprops.py
pimpmyclass/helpers.py
pimpmyclass/methods.py
pimpmyclass/mixins.py
pimpmyclass/props.py
pimpmyclass/stats.py
pimpmyclass.egg-info/PKG-INFO
pimpmyclass.egg-info/SOURCES.txt
pimpmyclass.egg-info/dependency_links.txt
pimpmyclass.egg-info/top_level.txt
pimpmyclass.egg-info/zip-safe
pimpmyclass/testsuite/__init__.py
pimpmyclass/testsuite/test_dictprops.py
pimpmyclass/testsuite/test_helpers.py
pimpmyclass/testsuite/test_methods.py
pimpmyclass/testsuite/test_props.py
pimpmyclass/testsuite/test_stats.py