Metadata-Version: 1.2
Name: pimpmyclass
Version: 0.4
Summary: Pimp your Class/Property/Methods with useful functionality
Home-page: https://github.com/hgrecco/pimpmyclass
Author: Hernan E. Grecco
Author-email: hernan.grecco@gmail.com
License: BSD
Keywords: classes properties descriptors decorators
Platform: UNKNOWN
Classifier: Development Status :: 4 - Beta
Classifier: Intended Audience :: Developers
Classifier: License :: OSI Approved :: BSD License
Classifier: Operating System :: MacOS :: MacOS X
Classifier: Operating System :: Microsoft :: Windows
Classifier: Operating System :: POSIX
Classifier: Programming Language :: Python
Classifier: Topic :: Scientific/Engineering
Classifier: Topic :: Software Development :: Libraries
Classifier: Programming Language :: Python :: 3.6
Classifier: Programming Language :: Python :: 3.7
Requires-Python: >=3.6
